factoreally/__init__.py
factoreally/__main__.py
factoreally/cli.py
factoreally/constants.py
factoreally/create_spec.py
factoreally/extract.py
factoreally/factory.py
factoreally/factory_spec.py
factoreally/json_spec.py
factoreally/py.typed
factoreally/pydantic_models.py
factoreally/analyzers/__init__.py
factoreally/analyzers/array_analyzer.py
factoreally/analyzers/base.py
factoreally/analyzers/choice_analyzer.py
factoreally/analyzers/null_analyzer.py
factoreally/analyzers/number_analyzer.py
factoreally/analyzers/object_analyzer.py
factoreally/analyzers/presence_analyzer.py
factoreally/analyzers/string_pattern_analyzer.py
factoreally/hints/__init__.py
factoreally/hints/alphanumeric_hint.py
factoreally/hints/array_hint.py
factoreally/hints/auth0_id_hint.py
factoreally/hints/base.py
factoreally/hints/choice_hint.py
factoreally/hints/constant_value_hint.py
factoreally/hints/date_hint.py
factoreally/hints/datetime_hint.py
factoreally/hints/duration_range_hint.py
factoreally/hints/mac_address_hint.py
factoreally/hints/missing_hint.py
factoreally/hints/null_hint.py
factoreally/hints/number_hint.py
factoreally/hints/number_string_hint.py
factoreally/hints/object_hint.py
factoreally/hints/text_hint.py
factoreally/hints/uuid4_hint.py
factoreally/hints/version_hint.py
factoreally-0.6.1.dist-info/METADATA
factoreally-0.6.1.dist-info/WHEEL
factoreally-0.6.1.dist-info/entry_points.txt
factoreally-0.6.1.dist-info/RECORD
