Metadata-Version: 2.4
Name: factoreally
Version: 0.6.1
Summary: Add your description here
Author-email: Raymond Butcher <randomy@gmail.com>
Requires-Python: >=3.12
Requires-Dist: click>=8.3.0
Requires-Dist: numpy>=2.3.3
Requires-Dist: pydantic>=2.11.9
Requires-Dist: scipy>=1.16.2
